eincraft/__init__.py
eincraft/core.py
eincraft-0.1.1.dist-info/licenses/LICENSE
eincraft-0.1.1.dist-info/METADATA
eincraft-0.1.1.dist-info/WHEEL
eincraft-0.1.1.dist-info/top_level.txt
eincraft-0.1.1.dist-info/RECORD
