Metadata-Version: 2.4
Name: eincraft
Version: 0.1.1
Summary: A library to simplify and automate einsum operations in a more intuitive way.
Author-email: Andrea Bianchi <andrea_bianchi@outlook.com>
License: MIT
Project-URL: Homepage, https://gitlab.com/andrea_bianchi/eincraft
Classifier: Programming Language :: Python :: 3
Classifier: License :: OSI Approved :: MIT License
Classifier: Operating System :: OS Independent
License-File: LICENSE
Requires-Dist: numpy
Dynamic: license-file
